{
  "user": [
    {
      "id": 1,
      "discriminacao": "aluno",
      "email": "oi@oi",
      "senha": "123",
      "nome": "José",
      "cpf": "12345678912",
      "nascimento": "2022-11-29T00:00:00",
      "descricao": "bem vindos ao meu koo"
    },
    {
      "id": 2,
      "discriminacao": "prof",
      "email": "oi@oi2",
      "senha": "123",
      "nome": "José",
      "cpf": "12345678912",
      "nascimento": "2022-11-29T00:00:00",
      "descricao": "bem vindos ao meu koo"
    }
  ]
}
